setup.py
django_images/__init__.py
django_images/models.py
django_images/settings.py
django_images/tests.py
django_images/urls.py
django_images/utils.py
django_images/views.py
django_images.egg-info/PKG-INFO
django_images.egg-info/SOURCES.txt
django_images.egg-info/dependency_links.txt
django_images.egg-info/not-zip-safe
django_images.egg-info/requires.txt
django_images.egg-info/top_level.txt
django_images/migrations/0001_initial.py
django_images/migrations/0002_change_thumbnail_unique_constraint.py
django_images/migrations/__init__.py
django_images/templatetags/__init__.py
django_images/templatetags/images.py